rs_fused_lib/__init__.py
rs_fused_lib/_load.py
rs_fused_lib/_run.py
rs_fused_lib/api/udf_api.py
rs_fused_lib/common/customJsonEncoder.py
rs_fused_lib/common/logger.py
rs_fused_lib/common/serializers.py
rs_fused_lib/config.py
rs_fused_lib/core/__init__.py
rs_fused_lib/core/udf.py
rs_fused_lib/data/__init__.py
rs_fused_lib/models/__init__.py
rs_fused_lib/types.py
rs_fused_lib/utils/__init__.py
rs_fused_lib/utils/read_util_file.py
rs_fused_lib/visualization/__init__.py
rs_fused_lib-0.1.5.dist-info/METADATA
rs_fused_lib-0.1.5.dist-info/WHEEL
rs_fused_lib-0.1.5.dist-info/RECORD
