Metadata-Version: 2.3
Name: rs-fused-lib
Version: 0.1.5
Summary: A Python library for RS fused operations
Author: rsDev-zh
Requires-Python: >=3.10,<4.0
Classifier: Programming Language :: Python :: 3
Classifier: Programming Language :: Python :: 3.10
Classifier: Programming Language :: Python :: 3.11
Classifier: Programming Language :: Python :: 3.12
Classifier: Programming Language :: Python :: 3.13
Requires-Dist: numpy (>=1.24.0,<2.0.0)
Requires-Dist: pandas (>=2.0.0,<3.0.0)
Requires-Dist: requests (>=2.0.0,<3.0.0)
